{"@context":"https://iiif.io/api/presentation/3/context.json","id":"https://mathewjordan.github.io/football-sample/api/facet/subject/bernstein-leonard-1918-1990-west-side-story.json","type":"Collection","label":{"none":["Bernstein, Leonard, 1918-1990. West Side story"]},"items":[{"id":"https://api.dc.library.northwestern.edu/api/v2/works/51aec647-176c-4344-b378-0c0b5657e33b?as=iiif","type":"Manifest","label":{"none":["SAGA, 1994 to 1995"]},"thumbnail":[{"id":"https://api.dc.library.northwestern.edu/api/v2/works/51aec647-176c-4344-b378-0c0b5657e33b/thumbnail","type":"Image","format":"image/jpeg","height":300,"width":300}],"homepage":[{"id":"https://mathewjordan.github.io/football-sample/works/saga-1994-to-1995","type":"Text","label":{"none":["SAGA, 1994 to 1995"]}}]}],"partOf":[{"id":"https://mathewjordan.github.io/football-sample/api/facet/subject.json","type":"Collection"}],"summary":{"none":["Subject"]},"homepage":[{"id":"https://mathewjordan.github.io/football-sample/search?subject=bernstein-leonard-1918-1990-west-side-story","type":"Text","label":{"none":["Bernstein, Leonard, 1918-1990. West Side story"]}}]}