{"@context":"https://iiif.io/api/presentation/3/context.json","id":"https://mathewjordan.github.io/football-sample/api/facet/subject/children.json","type":"Collection","label":{"none":["Children"]},"items":[{"id":"https://api.dc.library.northwestern.edu/api/v2/works/55a100c5-b1b4-4ec2-a509-41409d16ca64?as=iiif","type":"Manifest","label":{"none":["Children playing soccer"]},"thumbnail":[{"id":"https://api.dc.library.northwestern.edu/api/v2/works/55a100c5-b1b4-4ec2-a509-41409d16ca64/thumbnail","type":"Image","format":"image/jpeg","height":300,"width":300}],"homepage":[{"id":"https://mathewjordan.github.io/football-sample/works/children-playing-soccer","type":"Text","label":{"none":["Children playing soccer"]}}]}],"partOf":[{"id":"https://mathewjordan.github.io/football-sample/api/facet/subject.json","type":"Collection"}],"summary":{"none":["Subject"]},"homepage":[{"id":"https://mathewjordan.github.io/football-sample/search?subject=children","type":"Text","label":{"none":["Children"]}}]}